{
	"name": "removeduplicates",
	"properties": {
		"type": "MappingDataFlow",
		"typeProperties": {
			"sources": [
				{
					"dataset": {
						"referenceName": "customer_dataset",
						"type": "DatasetReference"
					},
					"name": "source1"
				}
			],
			"sinks": [
				{
					"dataset": {
						"referenceName": "output2dataset",
						"type": "DatasetReference"
					},
					"name": "sink1"
				}
			],
			"transformations": [
				{
					"name": "aggregate1"
				}
			],
			"scriptLines": [
				"source(output(",
				"          Name as string,",
				"          { ID} as string,",
				"          LOC as string,",
				"          SAL as string",
				"     ),",
				"     allowSchemaDrift: true,",
				"     validateSchema: false,",
				"     ignoreNoFilesFound: false) ~> source1",
				"source1 aggregate(each(match(name!='sal'), $$ = first($$))) ~> aggregate1",
				"aggregate1 sink(allowSchemaDrift: true,",
				"     validateSchema: false,",
				"     input(",
				"          Name as string,",
				"          Category as string,",
				"          Status as string,",
				"          Error as string",
				"     ),",
				"     skipDuplicateMapInputs: true,",
				"     skipDuplicateMapOutputs: true) ~> sink1"
			]
		}
	}
}